dearsj/__init__.py
dearsj-0.2.1.dist-info/LICENSE
dearsj-0.2.1.dist-info/WHEEL
dearsj-0.2.1.dist-info/METADATA
dearsj-0.2.1.dist-info/RECORD
